chATLAS_Embed/Base.py
chATLAS_Embed/Document.py
chATLAS_Embed/DocumentChunker.py
chATLAS_Embed/DocumentLoaders.py
chATLAS_Embed/EmbeddingModels.py
chATLAS_Embed/LangChainVectorStore.py
chATLAS_Embed/TextSplitters.py
chATLAS_Embed/TwikiProcessors.py
chATLAS_Embed/VectorStores.py
chATLAS_Embed/__init__.py
chATLAS_Embed/custom_stop_words.py
chATLAS_Embed/finetune/generation.py
chATLAS_Embed/finetune/openai_client.py
chATLAS_Embed/process_md/__init__.py
chATLAS_Embed/process_md/admonitions.py
chATLAS_Embed/process_md/analyse_chunks.py
chATLAS_Embed/process_md/chunker.py
chATLAS_Embed/process_md/content_tabs.py
chATLAS_Embed/process_md/data_structures.py
chATLAS_Embed/process_md/html_utils.py
chATLAS_Embed/process_md/long_tokens.py
chATLAS_Embed/process_md/preprocess.py
chATLAS_Embed/process_md/split_text.py
chATLAS_Embed/process_md/structural_blocks.py
chatlas_embed-0.1.19.dist-info/licenses/LICENSE
tests/__init__.py
tests/test_text_splitters.py
tests/db/test_db_build_query_dumped.py
tests/db/test_db_build_query_scraped_twiki.py
tests/db/test_db_complex.py
tests/db/test_db_markdown.py
tests/db/test_db_simple.py
tests/process_md/test_admonitions.py
tests/process_md/test_chunker.py
tests/process_md/test_content_tabs.py
tests/process_md/test_long_tokens.py
tests/process_md/test_md_process.py
tests/process_md/test_split_text.py
tests/process_md/test_structural_blocks.py
chatlas_embed-0.1.19.dist-info/METADATA
chatlas_embed-0.1.19.dist-info/WHEEL
chatlas_embed-0.1.19.dist-info/top_level.txt
chatlas_embed-0.1.19.dist-info/RECORD
