Metadata-Version: 2.4
Name: chATLAS_Embed
Version: 0.1.19
Summary: A modular Python package for efficient embedding workflows and PostgreSQL-based vector store management with parent-child relationships.
Author-email: Ben Elliot <Ben.Elliot27@outlook.com>
License: Apache-2.0
Project-URL: Homepage, https://gitlab.cern.ch/belliot/chatlas-packages/
Project-URL: Documentation, https://chatlas-packages.docs.cern.ch/chATLAS_Embed/
Classifier: Programming Language :: Python :: 3
Classifier: License :: OSI Approved :: Apache Software License
Classifier: Operating System :: OS Independent
Requires-Python: >=3.11
License-File: LICENSE
Requires-Dist: langchain~=0.3.3
Requires-Dist: beautifulsoup4~=4.12.2
Requires-Dist: tqdm~=4.66.5
Requires-Dist: SQLAlchemy~=2.0.35
Requires-Dist: spacy~=3.8.7
Requires-Dist: pydantic~=2.9.2
Requires-Dist: sentence_transformers~=3.2.0
Requires-Dist: pathlib
Requires-Dist: aiohttp~=3.10.10
Requires-Dist: psycopg2-binary~=2.9.10
Requires-Dist: torch~=2.2.1; sys_platform == "darwin" and platform_machine == "x86_64"
Requires-Dist: langchain_core
Requires-Dist: dataclasses
Requires-Dist: numpy
Requires-Dist: requests~=2.32.3
Requires-Dist: openai==1.99.9
Requires-Dist: matplotlib>=3.10.5
Requires-Dist: pandas
Requires-Dist: pip>=25.2
Dynamic: license-file
